kirrupt_tv
