Metadata-Version: 1.1
Name: kirrupt-tv
Version: 0.2
Summary: A Python client for the Kirrupt TV API.
Home-page: https://github.com/kirrupt/kirrupt-tv-python-client
Author: Kirrupt
Author-email: info@kirrupt.com
License: MIT
Platform: UNKNOWN
Classifier: Intended Audience :: Developers
Classifier: Operating System :: OS Independent
Classifier: Programming Language :: Python
Classifier: Topic :: Software Development :: Libraries :: Python Modules
